{
  "id": 15021,
  "zone_id": 150,
  "name": "The Servants' Corridor",
  "description": "You are standing in a corridor, that stretches further to the east.\nThere are doors to the north and west.  The corridor itself is mainly\nused by servants, and lacks some of the beauty of the rest of the\ncastle.",
  "header_raw": "150 d 0",
  "flags_text": "d",
  "sector": 0,
  "exits": [
    {
      "dir": 0,
      "description": "There is a door there!",
      "keywords": "door~ 1 -1 15026 D1 The corridor seems to come to its end a bit further east.",
      "door_flag": null,
      "key": null,
      "to": null
    },
    {
      "dir": 3,
      "description": "The door to the west is made out of wood.",
      "keywords": "door wood~ 1 -1 15020 S #15022 The End Of The Servants' Corridor~    The corridor leads only west from here, but there is a door to the north.",
      "door_flag": 150,
      "key": null,
      "to": 0
    },
    {
      "dir": 0,
      "description": "The door leads to a room intended for the butler.",
      "keywords": "door~ 1 15009 15027 D3 You see the corridor continue.",
      "door_flag": null,
      "key": null,
      "to": null
    }
  ],
  "extra_descriptions": [],
  "source_path": "/home/d3m4/dev/github/wardome/wdii/lib/world/wld/150.wld"
}