{
  "id": 2522,
  "zone_id": 25,
  "name": "A Damp Intersection",
  "description": "You are in a damp intersection of what seems to be the basement of\nthe tower.  The sound of running water can be heard coming from the\nsouth, other than that, an almost tangible stillness fills the air.\n   Passages lead off in all directions, and a ladder leads up.",
  "header_raw": "25 adg 0",
  "flags_text": "adg",
  "sector": 0,
  "exits": [
    {
      "dir": 0,
      "description": "",
      "keywords": "",
      "door_flag": 0,
      "key": -1,
      "to": 2523
    },
    {
      "dir": 1,
      "description": "A faint light can be seen in the distance up the east passage.",
      "keywords": "",
      "door_flag": 0,
      "key": -1,
      "to": 2524
    },
    {
      "dir": 2,
      "description": "",
      "keywords": "",
      "door_flag": 0,
      "key": -1,
      "to": 2525
    },
    {
      "dir": 3,
      "description": "",
      "keywords": "",
      "door_flag": 0,
      "key": -1,
      "to": 2526
    },
    {
      "dir": 4,
      "description": "",
      "keywords": "",
      "door_flag": 0,
      "key": -1,
      "to": 2521
    }
  ],
  "extra_descriptions": [],
  "source_path": "/home/d3m4/dev/github/wardome/wdii/lib/world/wld/25.wld"
}