{
  "id": 3553,
  "zone_id": 35,
  "name": "A Tunnel In The Mountains",
  "description": "The tunnel gets lighter to the north, presumably leading out, while to\nthe south the passage gets smaller and smaller.  A small alcove has been\ncarved into the east wall.",
  "header_raw": "35 a 1",
  "flags_text": "a",
  "sector": 1,
  "exits": [
    {
      "dir": 0,
      "description": "The tunnel gets wider in this direction.",
      "keywords": "",
      "door_flag": 0,
      "key": -1,
      "to": 3552
    },
    {
      "dir": 1,
      "description": "You see a small alcove.",
      "keywords": "",
      "door_flag": 0,
      "key": -1,
      "to": 3554
    },
    {
      "dir": 2,
      "description": "The tunnel gets smaller in this direction.",
      "keywords": "",
      "door_flag": 0,
      "key": -1,
      "to": 3555
    }
  ],
  "extra_descriptions": [],
  "source_path": "/home/d3m4/dev/github/wardome/wdii/lib/world/wld/35.wld"
}