{
  "id": 6110,
  "alias": "potion yellow musky",
  "short_desc": "a musky yellow potion",
  "long_desc": "A yellow potion has been left here.",
  "action_desc": "",
  "header_raw": "10 g 1",
  "values_raw": "15 39 -1 -1",
  "cost_raw": "2 1000 200",
  "extra_descriptions": [
    {
      "keywords": "potion yellow musky",
      "description": "It has a deep yellow color and and a strong spicy smell."
    }
  ],
  "affects": [],
  "source_path": "/home/d3m4/dev/github/wardome/wdii/lib/world/obj/61.obj"
}