{
  "id": 15009,
  "alias": "andrew guard royal",
  "short_desc": "Andrew",
  "long_desc": "Andrew the Royal Guard is here on duty.",
  "detailed_desc": "",
  "flags_raw": "As all members of the Guard, Andrew wears the chain mail required of",
  "stats1_raw": "them as uniform.  He seems very well trained, and moves like a fighter",
  "stats2_raw": "who has seen more than one battle, and longs to see the next!",
  "stats3_raw": "~",
  "source_path": "/home/d3m4/dev/github/wardome/wdii/lib/world/mob/150.mob"
}