{
  "id": 6114,
  "alias": "queen spider",
  "short_desc": "the Queen spider",
  "long_desc": "The huge, bulky Queen spider is here.",
  "detailed_desc": "",
  "flags_raw": "This disgusting creature is at the size of a small elephant.  It has eight",
  "stats1_raw": "huge, hairy legs that would give it a tremendous speed on almost any surface",
  "stats2_raw": "if it wasn't so immensely fat.  Its large, bulbous eyes stare back at you.",
  "stats3_raw": "~",
  "source_path": "/home/d3m4/dev/github/wardome/wdii/lib/world/mob/61.mob"
}